cw_rpa_unified_logger/Output/Result.txt
cw_rpa_unified_logger/__init__.py
cw_rpa_unified_logger/__main__.py
cw_rpa_unified_logger/poetry.lock
cw_rpa_unified_logger/src/__init__.py
cw_rpa_unified_logger/src/__main__.py
cw_rpa_unified_logger/src/loggers/__init__.py
cw_rpa_unified_logger/src/loggers/asio.py
cw_rpa_unified_logger/src/loggers/async_logger.py
cw_rpa_unified_logger/src/loggers/base.py
cw_rpa_unified_logger/src/loggers/config.py
cw_rpa_unified_logger/src/loggers/discord.py
cw_rpa_unified_logger/src/loggers/handlers.py
cw_rpa_unified_logger/src/loggers/local.py
cw_rpa_unified_logger/src/loggers/message_formatter.py
cw_rpa_unified_logger/src/loggers/setup_loggers.py
cw_rpa_unified_logger/src/loggers/types.py
cw_rpa_unified_logger/src/loggers/unified.py
cw_rpa_unified_logger/src/main.py
cw_rpa_unified_logger-0.1.0rc3.dist-info/LICENSE
cw_rpa_unified_logger-0.1.0rc3.dist-info/METADATA
cw_rpa_unified_logger-0.1.0rc3.dist-info/WHEEL
cw_rpa_unified_logger-0.1.0rc3.dist-info/RECORD
