Metadata-Version: 2.3
Name: cw-rpa-unified-logger
Version: 0.1.0rc3
Summary: Unified logging system with Discord and Asio integrations
License: MIT
Author: VinnyVanGogh
Author-email: 133192356+VinnyVanGogh@users.noreply.github.com
Requires-Python: >=3.11,<4.0
Classifier: License :: OSI Approved :: MIT License
Classifier: Programming Language :: Python :: 3
Classifier: Programming Language :: Python :: 3.11
Classifier: Programming Language :: Python :: 3.12
Classifier: Programming Language :: Python :: 3.13
Requires-Dist: aiohttp (>=3.11.11,<4.0.0)
Requires-Dist: colorlog (>=6.9.0,<7.0.0)
Requires-Dist: cw-rpa (>=0.1.0b10,<0.2.0)
